__init__.py
hello.py
gitty_py-0.1.0.dist-info/LICENSE
gitty_py-0.1.0.dist-info/METADATA
gitty_py-0.1.0.dist-info/WHEEL
gitty_py-0.1.0.dist-info/top_level.txt
gitty_py-0.1.0.dist-info/RECORD
